setup.cfg
setup.py
pycamhd.lazycache.egg-info/PKG-INFO
pycamhd.lazycache.egg-info/SOURCES.txt
pycamhd.lazycache.egg-info/dependency_links.txt
pycamhd.lazycache.egg-info/requires.txt
pycamhd.lazycache.egg-info/top_level.txt
pycamhd/lazycache/__init__.py
pycamhd/lazycache/lazycache.py
test/test_frame_count.py
test/test_get_frame.py