Metadata-Version: 1.2
Name: pycamhd.lazycache
Version: 0.1.0
Summary: Module for retrieving CamHD data through a LazyCache server
Home-page: https://github.com/CamHD-Analysis/pycamhd-lazycache
Author: Aaron Marburg
Author-email: amarburg@apl.washington.edu
License: MIT
Platform: UNKNOWN
Requires-Python: >=3
